{
    "validUser": {
        "firstName": "Octavio",
        "lastName": "Benitez",
        "email": "octavio.benitez@example.com",
        "password": "SecurePass123!",
        "confirmPassword": "SecurePass123!"
    },
    "mismatchedPasswordsUser": {
        "firstName": "Jesus",
        "lastName": "Medina",
        "email": "jesus.medina@example.com",
        "password": "Pass123",
        "confirmPassword": "DifferentPass"
    },
    "emptyFieldsUser": {
        "firstName": "",
        "lastName": "",
        "email": "",
        "password": "",
        "confirmPassword": ""
    },
    "invalidUser": {
        "email": "jhon.doe@example.com",
        "password": "incorrectPassword",
        "errorMessage": "Invalid email or password"
    },
    "invalidEmailFormatUser": {
        "email": "jhon.incorrect",
        "password": "SecurePass123!",
        "errorMessage": "Invalid email format"
    }
}